{
  "content": [
    {
      "content": null,
      "created": "2022-05-30T20:00:52.224700Z",
      "format": null,
      "last_modified": "2022-05-30T20:00:35.812494Z",
      "mimetype": null,
      "name": "odds_of_rolling_high_all_the_time.ipynb",
      "path": "stack_exchange/odds_of_rolling_high_all_the_time.ipynb",
      "size": 3365,
      "type": "notebook",
      "writable": true
    },
    {
      "content": null,
      "created": "2022-05-30T20:00:52.224700Z",
      "format": null,
      "last_modified": "2022-05-30T20:00:35.812494Z",
      "mimetype": null,
      "name": "contains_subset.ipynb",
      "path": "stack_exchange/contains_subset.ipynb",
      "size": 2365,
      "type": "notebook",
      "writable": true
    },
    {
      "content": null,
      "created": "2022-05-30T20:00:52.224700Z",
      "format": null,
      "last_modified": "2022-05-30T20:00:35.812494Z",
      "mimetype": null,
      "name": "green_red_elimination.ipynb",
      "path": "stack_exchange/green_red_elimination.ipynb",
      "size": 3888,
      "type": "notebook",
      "writable": true
    },
    {
      "content": null,
      "created": "2022-05-30T20:00:52.224700Z",
      "format": null,
      "last_modified": "2022-05-30T20:00:35.812494Z",
      "mimetype": null,
      "name": "all_action_stress.ipynb",
      "path": "stack_exchange/all_action_stress.ipynb",
      "size": 15147,
      "type": "notebook",
      "writable": true
    },
    {
      "content": null,
      "created": "2022-05-30T20:00:52.224700Z",
      "format": null,
      "last_modified": "2022-05-30T20:00:35.812494Z",
      "mimetype": null,
      "name": "dependent_dice_rolls.ipynb",
      "path": "stack_exchange/dependent_dice_rolls.ipynb",
      "size": 7126,
      "type": "notebook",
      "writable": true
    },
    {
      "content": null,
      "created": "2022-05-30T20:00:52.224700Z",
      "format": null,
      "last_modified": "2022-05-30T20:00:35.812494Z",
      "mimetype": null,
      "name": "risk_attrition.ipynb",
      "path": "stack_exchange/risk_attrition.ipynb",
      "size": 6131,
      "type": "notebook",
      "writable": true
    }
  ],
  "created": "2022-05-30T20:00:52.224700Z",
  "format": "json",
  "last_modified": "2022-05-30T20:00:52.224700Z",
  "mimetype": null,
  "name": "stack_exchange",
  "path": "stack_exchange",
  "size": null,
  "type": "directory",
  "writable": true
}